kairo/__init__.py
kairo/cli.py
kairo/constants.py
kairo/project.py
kairo/command/__init__.py
kairo/command/base.py
kairo/command/loader.py
kairo/projects/__init__.py
kairo/utils/__init__.py
kairo/utils/api.py
kairo-0.10.0.dist-info/METADATA
kairo-0.10.0.dist-info/WHEEL
kairo-0.10.0.dist-info/entry_points.txt
kairo-0.10.0.dist-info/licenses/LICENSE
kairo-0.10.0.dist-info/RECORD
