Metadata-Version: 2.3
Name: kairo
Version: 0.10.0
Summary: Kairo is a Python program that wraps API endpoints converting them to useful cli commands.
Author-email: Marco Espinosa <marco@marcoespinosa.com>
License: MIT License
License-File: LICENSE
Requires-Python: >=3.12
Requires-Dist: typer>=0.12.5
